{"CONJ 401":[["BIOL 220"],["CHEM 155","CHEM 162"]],"CONJ 402":[["CONJ 401"]],"CONJ 403":[["CONJ 402"]],"CONJ 475":[],"CONJ 480":[],"CONJ 504":[[" Graduate standing and permission of instructor."]],"CONJ 505":[[" first- or second-year medical student standing."]],"CONJ 510":[],"CONJ 511":[],"CONJ 512":[],"CONJ 513":[],"CONJ 514":[],"CONJ 515":[[" major standing in a health or human services profession."]],"CONJ 516":[],"CONJ 524":[[" undergraduate course in biochemistry and basic cell biology, or permission of instructor."]],"CONJ 526":[],"CONJ 529":[],"CONJ 530":[],"CONJ 531":[[" comprehensive undergraduate course in general biochemistry and molecular biology, or permission of instructor."]],"CONJ 532":[[" basic knowledge of biochemistry."]],"CONJ 533":[[" cell biology, biochemistry, and genetics."]],"CONJ 534":[],"CONJ 537":[],"CONJ 538":[[" permission of instructor"]],"CONJ 539":[],"CONJ 540":[[" biological science course"]],"CONJ 541":[[" comprehensive undergraduate course in biochemistry and molecular biology or permission of instructor."]],"CONJ 542":[[" comprehensive undergraduate courses in biology, molecular biology, or permission of instructor."]],"CONJ 544":[[" introductory biochemistry and cell biology"]],"CONJ 545":[],"CONJ 546":[],"CONJ 547":[],"CONJ 548":[],"CONJ 549":[[" advanced undergraduates with permission of instructor."]],"CONJ 550":[],"CONJ 551":[],"CONJ 552":[[" undergraduate organic chemistry and biochemistry"]],"CONJ 553":[],"CONJ 554":[],"CONJ 556":[],"CONJ 557":[["MICROM 412"]],"CONJ 558":[],"CONJ 559":[],"CONJ 562":[],"CONJ 570":[[" current graduate health science student and permission of course coordinator."]],"CONJ 583":[],"CONJ 585":[[" permission of department."]],"CONJ 616":[[" completion of the medicine and family medicine required clerkships."]],"CONJ 617":[],"CONJ 625":[[" fourth year medical students."]],"CONJ 626":[],"CONJ 630":[["WRITE "]],"CONJ 655":[],"CONJ 656":[],"CONJ 657":[],"CONJ 658":[],"CONJ 659":[],"CONJ 660":[],"CONJ 661":[],"CONJ 662":[],"CONJ 663":[],"CONJ 664":[],"CONJ 665":[],"CONJ 666":[],"CONJ 667":[],"CONJ 668":[],"CONJ 669":[],"CONJ 670":[],"CONJ 671":[],"CONJ 672":[],"CONJ 673":[],"CONJ 674":[],"CONJ 675":[],"CONJ 677":[["MED 665"]],"CONJ 679":[],"CONJ 680":[[" Completion of 3rd year psychiatry clerkship"]],"CONJ 681":[],"CONJ 682":[],"CONJ 683":[],"CONJ 684":[],"CONJ 685":[],"CONJ 686":[],"CONJ 687":[],"CONJ 688":[],"CONJ 689":[],"CONJ 690":[],"CONJ 691":[],"CONJ 692":[],"CONJ 693":[],"CONJ 694":[],"CONJ 695":[],"CONJ 696":[],"CONJ 697":[],"CONJ 698":[[" permission of Associate Dean for Academic Affairs, School of Medicine"]],"CONJ 699":[]}
