{"POLS 101":[],"POLS 110":[],"POLS 195":[],"POLS 201":[],"POLS 202":[],"POLS 203":[],"POLS 204":[],"POLS 205":[],"POLS 207":[],"POLS 212":[],"POLS 213":[],"POLS 246":[],"POLS 249":[],"POLS 270":[],"POLS 273":[],"POLS 281":[],"POLS 295":[],"POLS 299":[],"POLS 301":[],"POLS 302":[],"POLS 303":[],"POLS 304":[],"POLS 305":[],"POLS 306":[],"POLS 307":[],"POLS 308":[],"POLS 309":[],"POLS 310":[],"POLS 311":[],"POLS 312":[["POL S 318","POL S 319"]],"POLS 313":[],"POLS 314":[],"POLS 315":[["AES 150","AFRAM 150","AFRAM 201","POL S 201"]],"POLS 316":[],"POLS 317":[],"POLS 318":[["POL S 312"]],"POLS 319":[["POL S 312"]],"POLS 320":[],"POLS 321":[],"POLS 322":[],"POLS 324":[],"POLS 325":[],"POLS 326":[],"POLS 327":[],"POLS 328":[],"POLS 329":[],"POLS 330":[],"POLS 331":[],"POLS 332":[],"POLS 333":[],"POLS 334":[],"POLS 335":[],"POLS 337":[],"POLS 338":[],"POLS 340":[],"POLS 341":[],"POLS 342":[],"POLS 343":[],"POLS 346":[],"POLS 348":[],"POLS 350":[],"POLS 351":[],"POLS 352":[],"POLS 353":[],"POLS 354":[],"POLS 355":[],"POLS 356":[],"POLS 357":[],"POLS 358":[],"POLS 359":[],"POLS 360":[],"POLS 361":[],"POLS 363":[],"POLS 365":[],"POLS 367":[],"POLS 368":[],"POLS 370":[],"POLS 381":[],"POLS 382":[],"POLS 383":[],"POLS 384":[],"POLS 385":[],"POLS 395":[],"POLS 398":[],"POLS 401":[],"POLS 402":[],"POLS 403":[],"POLS 404":[],"POLS 405":[],"POLS 406":[],"POLS 407":[],"POLS 409":[],"POLS 410":[],"POLS 411":[],"POLS 412":[],"POLS 413":[],"POLS 414":[],"POLS 415":[],"POLS 416":[["ECON 300"]],"POLS 417":[],"POLS 418":[],"POLS 419":[],"POLS 420":[],"POLS 421":[],"POLS 422":[],"POLS 424":[],"POLS 425":[],"POLS 426":[],"POLS 427":[],"POLS 428":[],"POLS 429":[],"POLS 430":[],"POLS 431":[],"POLS 432":[],"POLS 433":[],"POLS 434":[],"POLS 435":[],"POLS 436":[],"POLS 437":[],"POLS 438":[],"POLS 439":[],"POLS 440":[],"POLS 441":[],"POLS 442":[],"POLS 443":[],"POLS 444":[],"POLS 445":[],"POLS 447":[],"POLS 448":[],"POLS 449":[],"POLS 451":[],"POLS 452":[],"POLS 453":[],"POLS 454":[],"POLS 455":[],"POLS 456":[],"POLS 457":[["POL S 249","HIST 249","SOC 266"]],"POLS 460":[],"POLS 461":[],"POLS 462":[["POL S 360","POL S 361"]],"POLS 464":[],"POLS 465":[],"POLS 467":[],"POLS 468":[],"POLS 469":[],"POLS 470":[],"POLS 471":[],"POLS 472":[],"POLS 473":[],"POLS 474":[],"POLS 475":[],"POLS 476":[],"POLS 477":[["POL S 204"]],"POLS 479":[],"POLS 480":[],"POLS 481":[],"POLS 488":[],"POLS 489":[],"POLS 495":[],"POLS 496":[],"POLS 497":[],"POLS 498":[],"POLS 499":[],"POLS 500":[],"POLS 501":[],"POLS 502":[],"POLS 503":[],"POLS 504":[],"POLS 505":[],"POLS 509":[],"POLS 510":[["POL S 501","SS 501"],["POL S 503","SS 503"]],"POLS 511":[],"POLS 513":[],"POLS 514":[[" permission of instructor"]],"POLS 515":[],"POLS 516":[],"POLS 517":[],"POLS 519":[],"POLS 520":[],"POLS 521":[],"POLS 522":[["POL S 521"]],"POLS 524":[],"POLS 525":[],"POLS 526":[],"POLS 527":[],"POLS 530":[],"POLS 532":[],"POLS 533":[["POL S 532"]],"POLS 534":[],"POLS 535":[[" a course on contemporary Chinese politics or history, or permission of instructor."]],"POLS 537":[[" permission of instructor."]],"POLS 538":[],"POLS 539":[[" permission of instructor."]],"POLS 540":[],"POLS 541":[],"POLS 542":[],"POLS 543":[],"POLS 544":[],"POLS 547":[],"POLS 548":[],"POLS 549":[],"POLS 550":[],"POLS 551":[],"POLS 552":[],"POLS 553":[],"POLS 554":[],"POLS 555":[],"POLS 556":[],"POLS 557":[],"POLS 558":[],"POLS 559":[],"POLS 560":[],"POLS 561":[],"POLS 562":[],"POLS 563":[],"POLS 564":[],"POLS 565":[],"POLS 566":[],"POLS 567":[],"POLS 569":[],"POLS 570":[],"POLS 571":[],"POLS 572":[],"POLS 573":[],"POLS 574":[],"POLS 575":[],"POLS 576":[],"POLS 577":[],"POLS 578":[],"POLS 579":[],"POLS 580":[],"POLS 582":[],"POLS 583":[],"POLS 584":[],"POLS 586":[],"POLS 587":[[" permission of instructor"]],"POLS 588":[],"POLS 589":[],"POLS 590":[],"POLS 593":[],"POLS 594":[],"POLS 595":[],"POLS 597":[],"POLS 598":[],"POLS 600":[],"POLS 800":[]}
